endaq/plot/__init__.py
endaq/plot/dashboards.py
endaq/plot/plots.py
endaq/plot/utilities.py
endaq_plot-1.1.0.dist-info/LICENSE
endaq_plot-1.1.0.dist-info/METADATA
endaq_plot-1.1.0.dist-info/WHEEL
endaq_plot-1.1.0.dist-info/top_level.txt
endaq_plot-1.1.0.dist-info/RECORD
