Metadata-Version: 2.1
Name: endaq-plot
Version: 1.1.0
Summary: A comprehensive, user-centric Python API for working with enDAQ data and devices
Home-page: https://github.com/MideTechnology/endaq-python
Author: Mide Technology
Author-email: help@mide.com
License: MIT
Keywords: ebml binary ide mide endaq
Platform: UNKNOWN
Classifier: Development Status :: 5 - Production/Stable
Classifier: License :: OSI Approved :: MIT License
Classifier: Natural Language :: English
Classifier: Programming Language :: Python :: 3.5
Classifier: Programming Language :: Python :: 3.6
Classifier: Programming Language :: Python :: 3.7
Classifier: Programming Language :: Python :: 3.8
Classifier: Programming Language :: Python :: 3.9
Classifier: Topic :: Scientific/Engineering
License-File: LICENSE
Requires-Dist: numpy (>=1.19.5)
Requires-Dist: pandas (>=1.1.5)
Requires-Dist: plotly (>=5.3.1)
Requires-Dist: scipy (>=1.7.1)
Requires-Dist: endaq-calc (>=1.1.0)
Provides-Extra: example
Requires-Dist: numpy (>=1.19.5) ; extra == 'example'
Requires-Dist: pandas (>=1.1.5) ; extra == 'example'
Requires-Dist: plotly (>=5.3.1) ; extra == 'example'
Requires-Dist: scipy (>=1.7.1) ; extra == 'example'
Requires-Dist: endaq-calc (>=1.1.0) ; extra == 'example'
Provides-Extra: test
Requires-Dist: numpy (>=1.19.5) ; extra == 'test'
Requires-Dist: pandas (>=1.1.5) ; extra == 'test'
Requires-Dist: plotly (>=5.3.1) ; extra == 'test'
Requires-Dist: scipy (>=1.7.1) ; extra == 'test'
Requires-Dist: endaq-calc (>=1.1.0) ; extra == 'test'
